enolib/__init__.py
enolib/analyzer.py
enolib/constants.py
enolib/context.py
enolib/error_types.py
enolib/grammar_regex.py
enolib/lookup.py
enolib/parse.py
enolib/register.py
enolib/resolver.py
enolib/elements/__init__.py
enolib/elements/element.py
enolib/elements/element_base.py
enolib/elements/empty.py
enolib/elements/field.py
enolib/elements/fieldset.py
enolib/elements/fieldset_entry.py
enolib/elements/list.py
enolib/elements/list_item.py
enolib/elements/section.py
enolib/elements/section_element.py
enolib/elements/value_element_base.py
enolib/elements/missing/__init__.py
enolib/elements/missing/missing_element_base.py
enolib/elements/missing/missing_empty.py
enolib/elements/missing/missing_field.py
enolib/elements/missing/missing_fieldset.py
enolib/elements/missing/missing_fieldset_entry.py
enolib/elements/missing/missing_list.py
enolib/elements/missing/missing_section.py
enolib/elements/missing/missing_section_element.py
enolib/elements/missing/missing_value_element_base.py
enolib/errors/__init__.py
enolib/errors/parsing.py
enolib/errors/selections.py
enolib/errors/validation.py
enolib/locales/__init__.py
enolib/locales/de.py
enolib/locales/en.py
enolib/locales/es.py
enolib/reporters/__init__.py
enolib/reporters/html_reporter.py
enolib/reporters/reporter.py
enolib/reporters/terminal_reporter.py
enolib/reporters/text_reporter.py
enolib-0.8.1.dist-info/LICENSE.txt
enolib-0.8.1.dist-info/METADATA
enolib-0.8.1.dist-info/WHEEL
enolib-0.8.1.dist-info/top_level.txt
enolib-0.8.1.dist-info/RECORD
