Metadata-Version: 2.1
Name: enolib
Version: 0.8.1
Summary: The eno standard library
Home-page: https://eno-lang.org/enolib/
Author: Simon Repp
Author-email: simon@fdpl.io
License: MIT
Platform: UNKNOWN
Classifier: Programming Language :: Python :: 3
Classifier: Programming Language :: Python :: 3.6
Classifier: License :: OSI Approved :: MIT License
Classifier: Operating System :: OS Independent
Classifier: Topic :: Software Development :: Libraries
